pytainer/__about__.py
pytainer/__init__.py
pytainer/cli.py
pytainer/models/__init__.py
pytainer/models/gittypes.py
pytainer/models/portainer.py
pytainer-0.0.5.dist-info/METADATA
pytainer-0.0.5.dist-info/WHEEL
pytainer-0.0.5.dist-info/entry_points.txt
pytainer-0.0.5.dist-info/licenses/LICENSE
pytainer-0.0.5.dist-info/RECORD
